{
  "ui.menu.play": "[PT] Play",
  "ui.menu.settings": "[PT] Settings",
  "ui.menu.quit": "[PT] Quit",
  "ui.common.confirm": "[PT] Confirm",
  "ui.common.cancel": "[PT] Cancel",
  "ui.common.ok": "[PT] OK",
  "ui.common.back": "[PT] Back",
  "ui.common.loading": "[PT] Loading...",
  "ui.common.error": "[PT] Error",
  "ui.common.retry": "[PT] Retry",
  "ui.common.close": "[PT] Close",
  "ui.common.max": "[PT] MAX",
  "ui.common.locked": "[PT] Locked",
  "ui.common.claim": "[PT] Claim",
  "ui.common.collect": "[PT] Collect",
  "ui.combat.energy": "[PT] Energy",
  "ui.combat.turn": "[PT] Turn {0}",
  "ui.combat.victory": "[PT] Victory!",
  "ui.combat.defeat": "[PT] Defeat",
  "ui.combat.draw": "[PT] Draw",
  "ui.combat.draw_phase": "[PT] Draw Phase",
  "ui.combat.action_phase": "[PT] Action Phase",
  "ui.combat.resolve_phase": "[PT] Resolving...",
  "ui.combat.your_turn": "[PT] Your Turn",
  "ui.combat.enemy_turn": "[PT] Enemy Turn",
  "ui.combat.critical_hit": "[PT] Critical Hit!",
  "ui.combat.miss": "[PT] Miss",
  "ui.combat.no_energy": "[PT] Not enough energy",
  "ui.combat.deck_empty": "[PT] Deck empty",
  "ui.combat.hand_full": "[PT] Hand full",
  "ui.empire.resources": "[PT] Resources",
  "ui.empire.buildings": "[PT] Buildings",
  "ui.empire.research": "[PT] Research",
  "ui.empire.build_queue": "[PT] Build Queue",
  "ui.empire.upgrade": "[PT] Upgrade",
  "ui.empire.build_time": "[PT] Build Time: {0}",
  "ui.empire.cost": "[PT] Cost",
  "ui.empire.production": "[PT] Production: {0}/hr",
  "ui.empire.max_level": "[PT] Max Level",
  "ui.empire.insufficient_resources": "[PT] Insufficient Resources",
  "ui.empire.queue_full": "[PT] Build queue full",
  "ui.empire.building_complete": "[PT] Building Complete!",
  "ui.alliance.chat": "[PT] Alliance Chat",
  "ui.alliance.war": "[PT] War",
  "ui.alliance.territory": "[PT] Territory",
  "ui.alliance.members": "[PT] Members",
  "ui.alliance.leaderboard": "[PT] Leaderboard",
  "ui.alliance.join": "[PT] Join Alliance",
  "ui.alliance.create": "[PT] Create Alliance",
  "ui.alliance.leave": "[PT] Leave Alliance",
  "ui.alliance.rally": "[PT] Rally Attack",
  "ui.alliance.donate": "[PT] Donate",
  "ui.alliance.war_starting": "[PT] War starting in {0}",
  "ui.alliance.territory_captured": "[PT] Territory captured!",
  "ui.heroes.roster": "[PT] Hero Roster",
  "ui.heroes.shards": "[PT] Shards: {0}/{1}",
  "ui.heroes.summon": "[PT] Summon",
  "ui.heroes.level_up": "[PT] Level Up",
  "ui.heroes.max_level": "[PT] Max Level Reached",
  "ui.heroes.star_up": "[PT] Star Up",
  "ui.heroes.locked": "[PT] Locked — Need {0} shards",
  "ui.heroes.equip": "[PT] Equip",
  "ui.heroes.stats": "[PT] Stats",
  "ui.heroes.abilities": "[PT] Abilities",
  "ui.economy.battle_pass": "[PT] Battle Pass",
  "ui.economy.shop": "[PT] Shop",
  "ui.economy.quests": "[PT] Quests",
  "ui.economy.daily_quests": "[PT] Daily Quests",
  "ui.economy.weekly_quests": "[PT] Weekly Quests",
  "ui.economy.premium_pass": "[PT] Premium Pass",
  "ui.economy.tier": "[PT] Tier {0}",
  "ui.economy.free_track": "[PT] Free Track",
  "ui.economy.premium_track": "[PT] Premium Track",
  "ui.economy.gacha": "[PT] Cosmetic Summon",
  "ui.economy.gacha_pity": "[PT] Pity: {0}/50",
  "ui.economy.purchase": "[PT] Purchase",
  "ui.economy.gems": "[PT] Gems",
  "ui.economy.restore_purchases": "[PT] Restore Purchases",
  "ui.settings.language": "[PT] Language",
  "ui.settings.sound": "[PT] Sound Effects",
  "ui.settings.music": "[PT] Music",
  "ui.settings.notifications": "[PT] Notifications",
  "ui.settings.graphics": "[PT] Graphics Quality",
  "ui.settings.colorblind": "[PT] Colorblind Mode",
  "ui.settings.colorblind.off": "[PT] Off",
  "ui.settings.colorblind.protanopia": "[PT] Protanopia",
  "ui.settings.colorblind.deuteranopia": "[PT] Deuteranopia",
  "ui.settings.colorblind.tritanopia": "[PT] Tritanopia",
  "ui.settings.haptics": "[PT] Haptic Feedback",
  "ui.settings.account": "[PT] Account",
  "ui.settings.privacy": "[PT] Privacy Policy",
  "ui.settings.tos": "[PT] Terms of Service",
  "ui.settings.support": "[PT] Customer Support",
  "ui.settings.version": "[PT] Version {0}",
  "tutorial.welcome": "[PT] Welcome to Ashen Throne!",
  "tutorial.first_build": "[PT] Tap a building slot to construct your first building.",
  "tutorial.first_battle": "[PT] Let's begin your first battle!",
  "tutorial.draw_cards": "[PT] Draw cards at the start of each turn.",
  "tutorial.play_card": "[PT] Tap a card, then tap a target to play it.",
  "tutorial.energy": "[PT] Cards cost energy. You regenerate {0} per turn.",
  "tutorial.hero_summon": "[PT] You've earned enough shards! Summon your new hero.",
  "tutorial.complete": "[PT] Tutorial complete! The throne awaits.",
  "ui.worldmap.territories": "[PT] Territories",
  "ui.worldmap.capture": "[PT] Capture Territory",
  "ui.worldmap.defend": "[PT] Defend",
  "ui.worldmap.neutral": "[PT] Neutral Territory",
  "ui.worldmap.supply_line": "[PT] Supply Line",
  "ui.worldmap.war_window": "[PT] War Window",
  "hero.lyra_thornveil.name": "[PT] Lyra Thornveil",
  "hero.lyra_thornveil.desc": "[PT] A nature mage who weaves vines and thorns to protect allies.",
  "hero.kael_ashwalker.name": "[PT] Kael Ashwalker",
  "hero.kael_ashwalker.desc": "[PT] A fire sorcerer who channels the fury of the Ashen Wastes.",
  "hero.thane_ironhold.name": "[PT] Thane Ironhold",
  "hero.thane_ironhold.desc": "[PT] An armored defender of the Iron Legion, unbreakable in battle.",
  "hero.zara_voidweaver.name": "[PT] Zara Voidweaver",
  "hero.zara_voidweaver.desc": "[PT] A void mystic who bends shadow to confuse and weaken foes.",
  "hero.rowan_stoneward.name": "[PT] Rowan Stoneward",
  "hero.rowan_stoneward.desc": "[PT] A steadfast guardian with the strength of living stone.",
  "hero.mira_frostbane.name": "[PT] Mira Frostbane",
  "hero.mira_frostbane.desc": "[PT] An ice mage whose frost slows all who oppose her.",
  "hero.vex_shadowstrike.name": "[PT] Vex Shadowstrike",
  "hero.vex_shadowstrike.desc": "[PT] A shadow assassin who strikes from the darkness.",
  "hero.sera_dawnblade.name": "[PT] Sera Dawnblade",
  "hero.sera_dawnblade.desc": "[PT] A holy knight radiating divine light to heal and smite.",
  "hero.grim_bonecrusher.name": "[PT] Grim Bonecrusher",
  "hero.grim_bonecrusher.desc": "[PT] A berserker who grows stronger as battle rages.",
  "hero.nyx_stormcaller.name": "[PT] Nyx Stormcaller",
  "hero.nyx_stormcaller.desc": "[PT] A lightning mage who chains destruction across the field.",
  "building.stronghold.name": "[PT] Stronghold",
  "building.stronghold.desc": "[PT] The heart of your empire. Upgrade to unlock new districts.",
  "building.barracks.name": "[PT] Barracks",
  "building.barracks.desc": "[PT] Train soldiers to bolster your military might.",
  "building.training_ground.name": "[PT] Training Ground",
  "building.training_ground.desc": "[PT] Sharpen your heroes' combat skills.",
  "building.watch_tower.name": "[PT] Watch Tower",
  "building.watch_tower.desc": "[PT] Provides early warning of incoming attacks.",
  "building.wall.name": "[PT] Wall",
  "building.wall.desc": "[PT] Stone fortifications protecting your city.",
  "building.armory.name": "[PT] Armory",
  "building.armory.desc": "[PT] Stores weapons and armor for your troops.",
  "building.stone_quarry.name": "[PT] Stone Quarry",
  "building.stone_quarry.desc": "[PT] Extracts stone from the mountainside.",
  "building.iron_mine.name": "[PT] Iron Mine",
  "building.iron_mine.desc": "[PT] Mines iron ore from deep underground.",
  "building.grain_farm.name": "[PT] Grain Farm",
  "building.grain_farm.desc": "[PT] Cultivates grain to feed your people.",
  "building.arcane_tower.name": "[PT] Arcane Tower",
  "building.arcane_tower.desc": "[PT] Harnesses magical essence from the ley lines.",
  "building.marketplace.name": "[PT] Marketplace",
  "building.marketplace.desc": "[PT] Trade goods to boost your economy.",
  "building.academy.name": "[PT] Academy",
  "building.academy.desc": "[PT] Research technologies to advance your empire.",
  "building.library.name": "[PT] Library",
  "building.library.desc": "[PT] Ancient knowledge speeds research.",
  "building.laboratory.name": "[PT] Laboratory",
  "building.laboratory.desc": "[PT] Experimental research for advanced upgrades.",
  "building.observatory.name": "[PT] Observatory",
  "building.observatory.desc": "[PT] Study the stars for strategic advantage.",
  "building.archive.name": "[PT] Archive",
  "building.archive.desc": "[PT] Preserves scrolls of forgotten lore.",
  "building.hero_shrine.name": "[PT] Hero Shrine",
  "building.hero_shrine.desc": "[PT] Honor fallen heroes to gain their blessing.",
  "building.guild_hall.name": "[PT] Guild Hall",
  "building.guild_hall.desc": "[PT] Coordinate with allies for joint operations.",
  "building.enchanting_tower.name": "[PT] Enchanting Tower",
  "building.enchanting_tower.desc": "[PT] Imbue equipment with magical properties.",
  "building.forge.name": "[PT] Forge",
  "building.forge.desc": "[PT] Craft weapons and armor from raw materials.",
  "building.embassy.name": "[PT] Embassy",
  "building.embassy.desc": "[PT] Establish diplomatic ties with other alliances.",
  "resource.stone": "[PT] Stone",
  "resource.iron": "[PT] Iron",
  "resource.grain": "[PT] Grain",
  "resource.arcane": "[PT] Arcane Essence",
  "resource.gold": "[PT] Gold",
  "resource.gems": "[PT] Gems",
  "quest.daily.collect_resources": "[PT] Collect {0} resources",
  "quest.daily.complete_battles": "[PT] Complete {0} battles",
  "quest.daily.upgrade_building": "[PT] Upgrade a building",
  "quest.daily.use_cards": "[PT] Play {0} ability cards",
  "quest.daily.alliance_chat": "[PT] Send a message in alliance chat",
  "quest.daily.login": "[PT] Log in today",
  "quest.weekly.win_battles": "[PT] Win {0} battles",
  "quest.weekly.research": "[PT] Complete a research",
  "quest.weekly.level_hero": "[PT] Level up a hero",
  "quest.weekly.pvp": "[PT] Complete {0} PvP battles",
  "quest.weekly.rally": "[PT] Participate in a rally",
  "quest.onetime.first_build": "[PT] Construct your first building",
  "quest.onetime.first_hero": "[PT] Summon your first hero",
  "quest.onetime.join_alliance": "[PT] Join an alliance",
  "quest.onetime.first_research": "[PT] Complete your first research",
  "quest.onetime.chapter_1": "[PT] Complete Chapter 1",
  "status.burn": "[PT] Burning",
  "status.freeze": "[PT] Frozen",
  "status.poison": "[PT] Poisoned",
  "status.shield": "[PT] Shielded",
  "status.stun": "[PT] Stunned",
  "status.slow": "[PT] Slowed",
  "status.enraged": "[PT] Enraged",
  "status.marked": "[PT] Marked",
  "status.heal_over_time": "[PT] Regenerating",
  "error.network": "[PT] Network error. Please check your connection.",
  "error.auth_failed": "[PT] Authentication failed. Please try again.",
  "error.purchase_failed": "[PT] Purchase failed: {0}",
  "error.server": "[PT] Server error. Please try again later.",
  "error.session_expired": "[PT] Session expired. Please log in again.",
  "notif.building_complete": "[PT] Your {0} is ready!",
  "notif.war_starting": "[PT] Alliance War starts in 30 minutes!",
  "notif.daily_reset": "[PT] Daily quests have reset!",
  "notif.battle_pass_expiring": "[PT] Battle Pass ends in {0} days",
  "notif.come_back": "[PT] Your troops miss you! Come back and claim resources.",
  "event.void_rift": "[PT] Void Rift",
  "event.void_rift.desc": "[PT] Dark portals have opened across the land. Defeat the void creatures!",
  "event.world_boss": "[PT] World Boss",
  "event.world_boss.desc": "[PT] A mighty beast threatens the realm. Rally your alliance!",
  "event.alliance_tournament": "[PT] Alliance Tournament",
  "event.alliance_tournament.desc": "[PT] Compete against other alliances for glory and rewards!",
  "event.launch_celebration": "[PT] Launch Celebration",
  "event.launch_celebration.desc": "[PT] Celebrate the launch of Ashen Throne with bonus rewards!"
}
